reeeeeeeeee/__init__.py
tests/__init__.py
tests/test_reeeeeeeeee.py
reeeeeeeeeeeeeeeee-0.3.0.dist-info/LICENSE
reeeeeeeeeeeeeeeee-0.3.0.dist-info/METADATA
reeeeeeeeeeeeeeeee-0.3.0.dist-info/WHEEL
reeeeeeeeeeeeeeeee-0.3.0.dist-info/entry_points.txt
reeeeeeeeeeeeeeeee-0.3.0.dist-info/top_level.txt
reeeeeeeeeeeeeeeee-0.3.0.dist-info/RECORD
